tierkreis_typecheck-0.2.0.dist-info/METADATA
tierkreis_typecheck-0.2.0.dist-info/WHEEL
tierkreis_typecheck/__init__.py
tierkreis_typecheck/__init__.pyi
tierkreis_typecheck/py.typed
tierkreis_typecheck/tierkreis_typecheck.cp310-win_amd64.pyd
tierkreis_typecheck-0.2.0.dist-info/RECORD
